tfinterpy/__init__.py
tfinterpy/grid.py
tfinterpy/idw.py
tfinterpy/krige.py
tfinterpy/utils.py
tfinterpy/variogram.py
tfinterpy/variogramExp.py
tfinterpy/variogramModel.py
tfinterpy/gslib/__init__.py
tfinterpy/gslib/fileUtils.py
tfinterpy/gui/__init__.py
tfinterpy/gui/canvas.py
tfinterpy/gui/tool.py
tfinterpy/gui/uiTool.py
tfinterpy/tf/__init__.py
tfinterpy/tf/commonLayer.py
tfinterpy/tf/idw.py
tfinterpy/tf/krige.py
tfinterpy/tf/variogramLayer.py
tfinterpy/vtk/__init__.py
tfinterpy/vtk/colorMap.py
tfinterpy/vtk/fileUtils.py
tfinterpy/vtk/rendering.py
TFInterpy-1.1.3.dist-info/LICENSE
TFInterpy-1.1.3.dist-info/METADATA
TFInterpy-1.1.3.dist-info/WHEEL
TFInterpy-1.1.3.dist-info/top_level.txt
TFInterpy-1.1.3.dist-info/RECORD
