Metadata-Version: 2.2
Name: TFInterpy
Version: 1.1.3
Summary: TFInterpy is a Python package for spatial interpolation. A high-performance version of several interpolation algorithms is implemented based on TensorFlow. Including parallelizable IDW and Kriging algorithms. So far, tfinterpy is the **fastest open source Kriging** algorithm, which can reduce the operation time of large-scale interpolation tasks by an order of magnitude.
Home-page: https://github.com/czwchenzhun/tfinterpy.git
Author: Zhiwen Chen
Author-email: orchenz@qq.com
Classifier: Programming Language :: Python :: 3
Classifier: License :: OSI Approved :: GNU General Public License v3 (GPLv3)
Classifier: Operating System :: OS Independent
License-File: LICENSE
Requires-Dist: numpy==2.0.2
Requires-Dist: scipy==1.13.1
Dynamic: author
Dynamic: author-email
Dynamic: classifier
Dynamic: description
Dynamic: description-content-type
Dynamic: home-page
Dynamic: requires-dist
Dynamic: summary
